mdapi_messages/__init__.py
mdapi_messages/base.py
mdapi_messages/messages.py
mdapi_messages/tests/__init__.py
mdapi_messages/tests/test_common.py
mdapi_messages/tests/test_messages.py
mdapi_messages/tests/utils.py
mdapi_messages-1.0.0.dist-info/LICENSE
mdapi_messages-1.0.0.dist-info/METADATA
mdapi_messages-1.0.0.dist-info/WHEEL
mdapi_messages-1.0.0.dist-info/entry_points.txt
mdapi_messages-1.0.0.dist-info/top_level.txt
mdapi_messages-1.0.0.dist-info/RECORD
